josecompiler/__init__.py
josecompiler/compiler.py
josecompiler-0.1.dist-info/METADATA
josecompiler-0.1.dist-info/WHEEL
josecompiler-0.1.dist-info/top_level.txt
josecompiler-0.1.dist-info/RECORD
