Metadata-Version: 2.1
Name: josecompiler
Version: 0.1
Summary: Um projeto simples de compilador.
Author: Jose Eduardo
Author-email: josedumoura@gmail.com
Classifier: Programming Language :: Python :: 3
Classifier: License :: OSI Approved :: MIT License
Classifier: Operating System :: OS Independent
Requires-Python: >=3.6
